flakow1stprojectdef/__init__.py
flakow1stprojectdef-0.1.0.dist-info/WHEEL
flakow1stprojectdef-0.1.0.dist-info/METADATA
flakow1stprojectdef-0.1.0.dist-info/RECORD
