Metadata-Version: 2.1
Name: flakow1stprojectdef
Version: 0.1.0
Summary: primeiro projetao caraio
Author: flakow
Author-email: tonyimportsmg@gmail.com
Requires-Python: >=3.10,<4.0
Classifier: Programming Language :: Python :: 3
Classifier: Programming Language :: Python :: 3.10
Classifier: Programming Language :: Python :: 3.11
